README.txt
setup.py
pyf/__init__.py
pyf.transport.egg-info/PKG-INFO
pyf.transport.egg-info/SOURCES.txt
pyf.transport.egg-info/dependency_links.txt
pyf.transport.egg-info/entry_points.txt
pyf.transport.egg-info/namespace_packages.txt
pyf.transport.egg-info/not-zip-safe
pyf.transport.egg-info/requires.txt
pyf.transport.egg-info/top_level.txt
pyf/transport/__init__.py
pyf/transport/packets.py