Metadata-Version: 1.0
Name: pyf.transport
Version: 2.0.1
Summary: DataFlow transport (packets) system for PyF framework
Home-page: http://pyfproject.org
Author: UNKNOWN
Author-email: UNKNOWN
License: MIT
Platform: UNKNOWN
Classifier: Programming Language :: Python
